odoo10_addon_l10n_hr_base_location-10.0.0.0.1-py2.7-nspkg.pth
odoo/addons/l10n_hr_base_location/README.rst
odoo/addons/l10n_hr_base_location/__init__.py
odoo/addons/l10n_hr_base_location/__manifest__.py
odoo/addons/l10n_hr_base_location/data/res.better.zip.csv
odoo/addons/l10n_hr_base_location/data/res_country_state_data.xml
odoo/addons/l10n_hr_base_location/static/description/icon.png
odoo10_addon_l10n_hr_base_location-10.0.0.0.1.dist-info/DESCRIPTION.rst
odoo10_addon_l10n_hr_base_location-10.0.0.0.1.dist-info/METADATA
odoo10_addon_l10n_hr_base_location-10.0.0.0.1.dist-info/RECORD
odoo10_addon_l10n_hr_base_location-10.0.0.0.1.dist-info/WHEEL
odoo10_addon_l10n_hr_base_location-10.0.0.0.1.dist-info/metadata.json
odoo10_addon_l10n_hr_base_location-10.0.0.0.1.dist-info/namespace_packages.txt
odoo10_addon_l10n_hr_base_location-10.0.0.0.1.dist-info/top_level.txt
